barl/__init__.py
barl/agents/__init__.py
barl/agents/baselines.py
barl/agents/interfaces.py
barl/agents/stateless_agents.py
barl/agents/stateless_bayesian.py
barl/environments/__init__.py
barl/environments/interfaces.py
barl/environments/multi_armed_bandit.py
barl/estimators/__init__.py
barl/estimators/baselines.py
barl/estimators/interfaces.py
barl/estimators/simple_bayesian.py
barl/simulations/__init__.py
barl/simulations/averaged_simulations.py
barl/simulations/basic_simulations.py
barl/types/__init__.py
barl/types/exceptions.py
barl/utils/__init__.py
barl/utils/numerical.py
barl/utils/plotting.py
barl/utils/utils.py
barl-0.0.0.5.dist-info/METADATA
barl-0.0.0.5.dist-info/RECORD
barl-0.0.0.5.dist-info/WHEEL
barl-0.0.0.5.dist-info/top_level.txt
