Metadata-Version: 2.1
Name: barl
Version: 0.0.0.5
Summary: Bayesian Approximate Reinforcement Learning (BARL)
Home-page: https://github.com/ai-nikolai/barl
Author: nikolai rozanov
Author-email: nikolai.rozanov@gmail.com
License: Apache 2.0
Platform: UNKNOWN
Requires-Python: >=3.6
Requires-Dist: numpy
Requires-Dist: matplotlib
Requires-Dist: seaborn (>=0.9)
